cwest_polymer/__init__.py
cwest_polymer/fmr_parameters.py
cwest_polymer/fmr_classes/__init__.py
cwest_polymer/fmr_classes/fmr_datasets.py
cwest_polymer/fmr_filereaders/__init__.py
cwest_polymer/fmr_filereaders/fmr_mass_spreadsheet_reader.py
cwest_polymer/fmr_filereaders/maldi_mass_list_reader.py
cwest_polymer/fmr_transforms/__init__.py
cwest_polymer/fmr_transforms/fmr_transforms.py
cwest_polymer-1.0.0.dist-info/LICENSE.txt
cwest_polymer-1.0.0.dist-info/METADATA
cwest_polymer-1.0.0.dist-info/WHEEL
cwest_polymer-1.0.0.dist-info/top_level.txt
cwest_polymer-1.0.0.dist-info/RECORD
