Metadata-Version: 2.2
Name: cwest-polymer
Version: 1.0.0
Summary: Functions to determine polymer groups within datasets using kendrick mass defect and mass remainder analysis.
Author-email: Cole Stapleton <cstapleton@mmm.com>, Matt Mills <mmills2@mmm.com>
Project-URL: Source, https://github.com/3mcloud/cwest-polymer
Project-URL: Issues, https://github.com/3mcloud/cwest-polymer/issues
Classifier: Development Status :: 1 - Planning
Classifier: Intended Audience :: Science/Research
Classifier: Natural Language :: English
Classifier: Operating System :: OS Independent
Classifier: Topic :: Scientific/Engineering :: Chemistry
Classifier: Topic :: Scientific/Engineering :: Physics
Classifier: Topic :: Scientific/Engineering :: Information Analysis
Classifier: Programming Language :: Python :: 3.9
Classifier: Programming Language :: Python :: 3.10
Classifier: Programming Language :: Python :: 3.11
Classifier: License :: OSI Approved :: MIT License
Requires-Python: <3.12,>=3.9
License-File: LICENSE.txt
Requires-Dist: bokeh
Requires-Dist: matplotlib
Requires-Dist: numpy
Requires-Dist: openpyxl
Requires-Dist: pandas
Requires-Dist: scikit-learn
Requires-Dist: scipy
Requires-Dist: molmass==2023.4.10
Requires-Dist: piblin==0.0.0a1
Requires-Dist: plotly>=6.0.1
Provides-Extra: tests
Requires-Dist: pytest==8.3.4; extra == "tests"
Requires-Dist: pytest-mpl==0.17.0; extra == "tests"
Requires-Dist: pytest-cov==6.0.0; extra == "tests"
Requires-Dist: pytest-html==4.1.1; extra == "tests"
